Workbook

Sheet PADRÃO
B2: Programa Dinheiro Direto na Escola (PDDE) | G2: PDDE
A3: Fundo Nacional de Desenvolvimento da Educação
A4: PLANILHA DE PESQUISA DE PREÇOS
A6: BLOCO I - IDENTIFICAÇÃO DA UNIDADE EXECUTORA PRÓPRIA (UEx)
A7: 1- UF: | B7: PA | C7: 2- Municipio: | G7: 3- Pesquisa nº: | H7: 1
A8: CONSELHO: | G8: CNPJ
A9: CONSELHO ESCOLAR DA ESCOLA RAQUEL FREIRE PAES | G9: 02.522.102/0001-00
A10: 6- Endereço:
A11: COMUNIDADESAO RAIMUNDO DO MOJU, SN
A12: BLOCO II - IDENTIFICAÇÃO DO DIRIGENTE OU DO RESPRESENTANTE LEGAL DA Uex
A13: 7- Nome do Dirigente ou do Representante Legal da Uex | G13: 8- Cargo:
G14: PRESIDENTE DO CONSELHO
A15: 9- Assinatura do Dirigente ou do Representante Legal da Uex | G15: 10- Telefone:
A17: 11- Nome da Empresa / Pessoa Física: | G17: 12- Data/hora:
J18: CONTROLE
A19: BLOCO III - PROPOSTAS
A20: 1 | J20: PREÇO COMPRAR | L20: VENDA
A21: 14-Item | B21: 15 - Descrição dos Produtos e Serviços | E21: 16-UND | F21: 17-Quant. | G21: 18-Valor Unit | H21: 19-Valor Total | J21: PREÇO COMPRAR | K21: VENDA COMPRAR TOTAL | L21: VALOR VENDA | M21: % | N21: % LUCRO
A22: 1 | B22: CAIXA AMP JBL PARTY BOX ENCORE C/2 MIC | E22: UN | F22: 1 | G22: 3318 | H22: =G22*F22 -> 3318 | K22: =F22*J22 -> 0 | L22: =J22*M22+J22 -> 0 | N22: =(H22-K22)/K22 -> 0
A23: 2
A24: 3
A25: 4
A26: 5
A27: 6
A28: 7
A29: 8
A30: 9
A31: 10
H32: =SUM(H22:H31) -> 3318 | J32: TOTAL COMPRAR | K32: =SUM(K22:K31) -> 0
A33: BLOCO IV - IDENTIFICAÇÃO DOS COMPONENTES (fornecedores de produtos ou prestadores de serviços)
J34: FINANCEIRO
J35: TAXA | K35: =H32*10% -> 331.8 | M35: BASE
A36: 22 - Endereço | G36: 23 - Municipio | H36: 24 - UF | J36: CLAUDIAN % | K36: =H32*3% -> 99.54 | M36: 0.35 | N36: LIMPEZA
J37: IMPOSTO R$ | K37: =H32*9% -> 298.62 | M37: 0.4 | N37: INFORMATICA
A38: 25 - CNPJ / CPF | F38: 26 - RG | J38: MAQUINETA R$ | M38: 0.5 | N38: EXPEDIENTE
J39: ENTREGA R$
A40: 27 - Assinatura e Carimbo do Representante Legal da Empresa | J40: TOTAL DESPESAS | K40: =K32+K35+K36+K37+K38+K39 -> 729.96
J41: LUCRO | K41: =H32-K40 -> 2588.04
A42: 25 - CNPJ / CPF | F42: 26 - RG | J42: LUCRO REAL | K42: =(H32-K40)/K40 -> 3.5454545
A44: 27 - Assinatura e Carimbo do Representante Legal da Empresa

Sheet BASE 02
B2: Programa Dinheiro Direto na Escola (PDDE) | G2: PDDE
A3: Fundo Nacional de Desenvolvimento da Educação
A4: PLANILHA DE PESQUISA DE PREÇOS
A6: BLOCO I - IDENTIFICAÇÃO DA UNIDADE EXECUTORA PRÓPRIA (UEx)
A7: 1- UF: | B7: PA | C7: 2- Municipio: | G7: 3- Pesquisa nº: | H7: 2
A9: =PADRÃO!A9 -> CONSELHO ESCOLAR DA ESCOLA RAQUEL FREIRE PAES | G9: =PADRÃO!G9 -> 02.522.102/0001-00
A10: 6- Endereço:
A11: COMUNIDADESAO RAIMUNDO DO MOJU, SN, 68129-00
A12: BLOCO II - IDENTIFICAÇÃO DO DIRIGENTE OU DO RESPRESENTANTE LEGAL DA Uex
A13: 7- Nome do Dirigente ou do Representante Legal da Uex | G13: 8- Cargo:
G14: =PADRÃO!G14 -> PRESIDENTE DO CONSELHO
A15: 9- Assinatura do Dirigente ou do Representante Legal da Uex | G15: 10- Telefone:
A17: 11- Nome da Empresa / Pessoa Física: | G17: 12- Data/hora:
A19: BLOCO III - PROPOSTAS
A20: 1
A21: 14-Item | B21: 15 - Descrição dos Produtos e Serviços | E21: 16-UND | F21: 17-Quant. | G21: 18-Valor Unit | H21: 19-Valor Total
A22: 1 | B22: =PADRÃO!B22 -> CAIXA AMP JBL PARTY BOX ENCORE C/2 MIC | E22: =PADRÃO!E22 -> UN | F22: =PADRÃO!F22 -> 1 | G22: =M22 -> 3351.18 | H22: =G22*F22 -> 3351.18 | J22: 5.89 | K22: =PADRÃO!G22 -> 3318 | L22: 1 | M22: =K22*L22/100+K22 -> 3351.18
A23: 2 | J23: 5.89 | K23: =PADRÃO!G23 | L23: 1 | M23: =K23*L23/100+K23 -> 0
A24: 3 | K24: =PADRÃO!G24 | L24: 2 | M24: =K24*L24/100+K24 -> 0
A25: 4 | K25: =PADRÃO!G25 | L25: 3 | M25: =K25*L25/100+K25 -> 0
A26: 5 | K26: =PADRÃO!G26 | L26: 1 | M26: =K26*L26/100+K26 -> 0
A27: 6 | K27: =PADRÃO!G27 | L27: 2 | M27: =K27*L27/100+K27 -> 0
A28: 7 | K28: =PADRÃO!G28 | L28: 1 | M28: =K28*L28/100+K28 -> 0
A29: 8 | K29: =PADRÃO!G29 | L29: 4 | M29: =K29*L29/100+K29 -> 0
A30: 9 | K30: =PADRÃO!G30 | L30: 1 | M30: =K30*L30/100+K30 -> 0
A31: 10 | K31: =PADRÃO!G31 | L31: 1 | M31: =K31*L31/100+K31 -> 0
H32: =SUM(H22:H31) -> 3351.18 | K32: =PADRÃO!G45 | L32: 1 | M32: =K32*L32/100+K32 -> 0
A33: BLOCO IV - IDENTIFICAÇÃO DOS COMPONENTES (fornecedores de produtos ou prestadores de serviços) | K33: =PADRÃO!G46 | L33: 1 | M33: =K33*L33/100+K33 -> 0
K34: =PADRÃO!G47 -> 0 | L34: 1 | M34: =K34*L34/100+K34 -> 0
K35: =PADRÃO!G48 -> 0 | L35: 1 | M35: =K35*L35/100+K35 -> 0
A36: 22 - Endereço | G36: 23 - Municipio | H36: 24 - UF | L36: 1 | M36: =K36*L36/100+K36 -> 0
L37: 1 | M37: =K37*L37/100+K37 -> 0
A38: 25 - CNPJ / CPF | F38: 26 - RG | L38: 1 | M38: =K38*L38/100+K38 -> 0
L39: 1 | M39: =K39*L39/100+K39 -> 0
A40: 27 - Assinatura e Carimbo do Representante Legal da Empresa | L40: 4 | M40: =K40*L40/100+K40 -> 0
L41: 4
A42: 25 - CNPJ / CPF | F42: 26 - RG
A44: 27 - Assinatura e Carimbo do Representante Legal da Empresa

Sheet BASE 03
B2: Programa Dinheiro Direto na Escola (PDDE) | G2: PDDE
A3: Fundo Nacional de Desenvolvimento da Educação
A4: PLANILHA DE PESQUISA DE PREÇOS
A6: BLOCO I - IDENTIFICAÇÃO DA UNIDADE EXECUTORA PRÓPRIA (UEx)
A7: 1- UF: | B7: PA | C7: 2- Municipio: | G7: 3- Pesquisa nº: | H7: 3
A8: ESCOLA | G8: CNPJ
A9: CONSELHO ESCOLAR DA ESCOLA MUNI ENS FUN PROF RAQUEL FREIRE PAES | G9: =PADRÃO!G9 -> 02.522.102/0001-00
A10: 6- Endereço:
A11: =PADRÃO!A11 -> COMUNIDADESAO RAIMUNDO DO MOJU, SN
A12: BLOCO II - IDENTIFICAÇÃO DO DIRIGENTE OU DO RESPRESENTANTE LEGAL DA Uex
A13: 7- Nome do Dirigente ou do Representante Legal da Uex | G13: 8- Cargo:
G14: =PADRÃO!G14 -> PRESIDENTE DO CONSELHO
A15: 9- Assinatura do Dirigente ou do Representante Legal da Uex | G15: 10- Telefone:
A17: 11- Nome da Empresa / Pessoa Física: | G17: 12- Data/hora:
A19: BLOCO III - PROPOSTAS
A20: 1
A21: 14-Item | B21: 15 - Descrição dos Produtos e Serviços | E21: 16-UND | F21: 17-Quant. | G21: 18-Valor Unit | H21: 19-Valor Total
A22: 1 | B22: =PADRÃO!B22 -> CAIXA AMP JBL PARTY BOX ENCORE C/2 MIC | E22: =PADRÃO!E22 -> UN | F22: =PADRÃO!F22 -> 1 | G22: =M22 -> 3417.54 | H22: =G22*F22 -> 3417.54 | J22: 5.89 | K22: =PADRÃO!G22 -> 3318 | L22: 3 | M22: =K22*L22/100+K22 -> 3417.54
A23: 2 | J23: 5.89 | K23: =PADRÃO!G23 | L23: 3 | M23: =K23*L23/100+K23 -> 0
A24: 3 | K24: =PADRÃO!G24 | L24: 4 | M24: =K24*L24/100+K24 -> 0
A25: 4 | K25: =PADRÃO!G25 | L25: 2 | M25: =K25*L25/100+K25 -> 0
A26: 5 | K26: =PADRÃO!G26 | L26: 4 | M26: =K26*L26/100+K26 -> 0
A27: 6 | K27: =PADRÃO!G27 | L27: 2 | M27: =K27*L27/100+K27 -> 0
A28: 7 | K28: =PADRÃO!G28 | L28: 2 | M28: =K28*L28/100+K28 -> 0
A29: 8 | K29: =PADRÃO!G29 | L29: 2 | M29: =K29*L29/100+K29 -> 0
A30: 9 | K30: =PADRÃO!G30 | L30: 2 | M30: =K30*L30/100+K30 -> 0
A31: 10 | K31: =PADRÃO!G31 | L31: 4 | M31: =K31*L31/100+K31 -> 0
H32: =SUM(H22:H31) -> 3417.54 | K32: =PADRÃO!G37 | L32: 4 | M32: =K32*L32/100+K32 -> 0
A33: BLOCO IV - IDENTIFICAÇÃO DOS COMPONENTES (fornecedores de produtos ou prestadores de serviços) | K33: =PADRÃO!G38 | L33: 6
L34: 6
L35: 6
A36: 22 - Endereço | G36: 23 - Municipio | H36: 24 - UF
A38: 25 - CNPJ / CPF | F38: 26 - RG
A40: 27 - Assinatura e Carimbo do Representante Legal da Empresa
A42: 25 - CNPJ / CPF | F42: 26 - RG
A44: 27 - Assinatura e Carimbo do Representante Legal da Empresa

Sheet JAYME BACESSART (2)
B2: Programa Dinheiro Direto na Escola (PDDE) | G2: PDDE
A3: Fundo Nacional de Desenvolvimento da Educação
A4: PLANILHA DE PESQUISA DE PREÇOS
A6: BLOCO I - IDENTIFICAÇÃO DA UNIDADE EXECUTORA PRÓPRIA (UEx)
A7: 1- UF: | B7: PA | C7: 2- Municipio: | D7: SANTARÉM | G7: 3- Pesquisa nº: | H7: 3
A9: CONSELHO ESCOLAR DA ESC. MUN. ENS. FUN. JAYME BARCESSAT | G9: 02.522.011/0001-67
A10: 6- Endereço:
A11: COM CURUA UMA, S/N - PLANALTO
A12: BLOCO II - IDENTIFICAÇÃO DO DIRIGENTE OU DO RESPRESENTANTE LEGAL DA Uex
A13: 7- Nome do Dirigente ou do Representante Legal da Uex | G13: 8- Cargo:
A15: 9- Assinatura do Dirigente ou do Representante Legal da Uex | G15: 10- Telefone:
A17: 11- Nome da Empresa / Pessoa Física: | G17: 12- Data/hora:
A19: BLOCO III - PROPOSTAS
A20: 13- Bens, Materiai ou Serviços
A21: 14-Item | B21: 15 - Descrição dos Produtos e Serviços | E21: 16-Unid. | F21: 17-Quant. | G21: 18-Valor Unit | H21: 19-Valor Total
A22: 01 | B22: CANETA DESTACA TEXTO | E22: CX | F22: 1
A23: 02
A24: 03
A25: 04
A26: 05
A27: 06
A28: 07
A29: 08
A30: 09
A31: 10
A32: 11
A33: 12
A34: 13
... A43: BLOCO IV - IDENTIFICAÇÃO DOS COMPONENTES (fornecedores de produtos ou prestadores de serviços)
A46: 22 - Endereço | G46: 23 - Municipio | H46: 24 - UF
A48: 25 - CNPJ / CPF | F48: 26 - RG
A50: 27 - Assinatura e Carimbo do Representante Legal da Empresa
A52: 25 - CNPJ / CPF | F52: 26 - RG
A54: 27 - Assinatura e Carimbo do Representante Legal da Empresa
